harmonize/__main__.py
harmonize/decoders.py
harmonize/encoders.py
harmonize-1.0.1.dist-info/LICENSE
harmonize-1.0.1.dist-info/METADATA
harmonize-1.0.1.dist-info/WHEEL
harmonize-1.0.1.dist-info/entry_points.txt
harmonize-1.0.1.dist-info/top_level.txt
harmonize-1.0.1.dist-info/RECORD
