Metadata-Version: 2.1
Name: harmonize
Version: 1.0.1
Summary: Create and synchronize transcoded copies of audio folders
Home-page: https://github.com/nvllsvm/harmonize
Author: Andrew Rabert
Author-email: ar@nullsum.net
License: Apache 2.0
Platform: UNKNOWN
Classifier: Development Status :: 4 - Beta
Classifier: Intended Audience :: End Users/Desktop
Classifier: License :: OSI Approved :: Apache Software License
Classifier: Programming Language :: Python :: 3 :: Only
Requires-Python: >=3.6
Requires-Dist: mutagen (>=1.40.0)
